README.md
setup.py
teapot/__init__.py
teapot/main.py
teapot/scorers.py
teapot/utils.py
teapot_nlp.egg-info/PKG-INFO
teapot_nlp.egg-info/SOURCES.txt
teapot_nlp.egg-info/dependency_links.txt
teapot_nlp.egg-info/entry_points.txt
teapot_nlp.egg-info/requires.txt
teapot_nlp.egg-info/top_level.txt
tests/__init__.py
tests/test_api.py
tests/test_scorers.py