Metadata-Version: 2.1
Name: teapot-nlp
Version: 0.2.1
Summary: Source and target side evaluation of adversarial attacks on NLP models
Home-page: https://github.com/pmichel31415/teapot-nlp
Author: Paul Michel
License: MIT
Platform: UNKNOWN
Classifier: Intended Audience :: Developers
Classifier: Topic :: Text Processing
Classifier: Topic :: Scientific/Engineering :: Artificial Intelligence
Classifier: License :: OSI Approved :: MIT License
Classifier: Programming Language :: Python :: 3
